{
  "date": "2026-02-03",
  "issues": {
    "open": 186,
    "closed_7d": 6,
    "closed_30d": 24,
    "closed_90d": 237,
    "opened_7d": 7,
    "opened_30d": 28,
    "opened_90d": 126,
    "without_response_24h": 59,
    "without_response_7d": 57,
    "without_response_30d": 52,
    "stale_30d": 142,
    "stale_60d": 53,
    "stale_90d": 45,
    "reopen_rate": 1,
    "response_time": {
      "avg_hours": 2721.2,
      "median_hours": 2687.5,
      "p90_hours": 5831.7,
      "p95_hours": 6222.6
    },
    "close_time": {
      "avg_days": 135.7,
      "median_days": 149.6,
      "p90_days": 254.5
    },
    "label_coverage_pct": 99.5
  },
  "pulls": {
    "open": 96,
    "merged_7d": 10,
    "merged_30d": 41,
    "merged_90d": 151,
    "opened_7d": 37,
    "opened_30d": 85,
    "opened_90d": 260,
    "closed_not_merged_90d": 107,
    "draft_count": 17,
    "without_review_24h": 54,
    "without_review_7d": 48,
    "review_time": {
      "avg_hours": 178.6,
      "median_hours": 13.4,
      "p90_hours": 552.2,
      "p95_hours": 907.2
    },
    "merge_time": {
      "avg_hours": 181.7,
      "median_hours": 12.6
    },
    "code_review_rate_pct": 92.1,
    "rejection_rate_pct": 41.5,
    "avg_reviews_per_pr": 3,
    "by_size": {
      "small": 32,
      "medium": 36,
      "large": 28
    }
  },
  "repository": {
    "stars": 11485,
    "forks": 1591
  },
  "contributors": {
    "total": 447,
    "active_30d": 53,
    "first_time_30d": 37,
    "retention_rate_pct": 100,
    "churned_30d": 0,
    "commits_per_week_avg": 11.1,
    "active_maintainers_30d": 11,
    "active_community_30d": 42
  }
}